LICENSE
README.md
setup.py
nlutils_mini/ExperimentLogger.py
nlutils_mini/Logger.py
nlutils_mini/ParallelTrain.py
nlutils_mini/__init__.py
nlutils_mini/color_utils.py
nlutils_mini/utils.py
nlutils_mini.egg-info/PKG-INFO
nlutils_mini.egg-info/SOURCES.txt
nlutils_mini.egg-info/dependency_links.txt
nlutils_mini.egg-info/requires.txt
nlutils_mini.egg-info/top_level.txt