Metadata-Version: 2.1
Name: nlutils-mini
Version: 0.0.6
Summary: Toolkit for neural learning training
Author: Nikola Liu
Author-email: nikolaliu@icloud.com
License-File: LICENSE
